cocotb_exmaple/src/simple_design.v
`timescale 1ns/1ns

module updown_counter
(
input clk,
input reset,
input [1:0]direction,
output [3:0] count
);

reg [3:0] counter = 0; 

always @(posedge clk)
begin
    if(reset) 
        counter <= 0;
    else if (direction == 2'b01)
        counter <= counter + 1;
    else if (direction == 2'b11)
        counter <= counter - 1; 
    else
        counter <= counter; 
end
    
assign count = counter;

// Dump waves
  initial begin
    $dumpfile("dump.vcd");
    $dumpvars(1, updown_counter);
    $printtimescale(updown_counter);
  end
endmodule

cocotb_exmaple/sim/dump.vcd
$date
	Fri Aug  4 13:26:23 2023
$end
$version
	Icarus Verilog
$end
$timescale
	1ps
$end
$scope module updown_counter $end
$var wire 1 ! clk $end
$var wire 4 " count [3:0] $end
$var wire 2 # direction [1:0] $end
$var wire 1 $ reset $end
$var reg 4 % counter [3:0] $end
$upscope $end
$enddefinitions $end
$comment Show the parameter values. $end
$dumpall
$end
#0
$dumpvars
b0 %
1$
b1 #
b0 "
1!
$end
#5000
0!
#10000
1!
#15000
0!
#20000
1!
#25000
0!
#30000
1!
#35000
0!
#40000
1!
#45000
0!
#50000
b1 "
b1 %
1!
0$
#55000
0!
#60000
b10 "
b10 %
1!
#65000
0!
#70000
b11 "
b11 %
1!
#75000
0!
#80000
b100 "
b100 %
1!
#85000
0!
#90000
b101 "
b101 %
1!
#95000
0!
#100000
b110 "
b110 %
1!
#105000
0!
#110000
b111 "
b111 %
1!
#115000
0!
#120000
b1000 "
b1000 %
1!
#125000
0!
#130000
b1001 "
b1001 %
1!
#135000
0!
#140000
b1010 "
b1010 %
1!
#145000
0!
#150000
b1011 "
b1011 %
1!
#155000
0!
#160000
b1100 "
b1100 %
1!
#165000
0!
#170000
b1101 "
b1101 %
1!
#175000
0!
#180000
b1110 "
b1110 %
1!
#185000
0!
#190000
b1111 "
b1111 %
1!
#195000
0!
#200000
b0 "
b0 %
1!
#205000
0!
#210000
b1 "
b1 %
1!
#215000
0!
#220000
b10 "
b10 %
1!
#225000
0!
#230000
b11 "
b11 %
1!
#235000
0!
#240000
b100 "
b100 %
1!
#245000
0!
#250000
b101 "
b101 %
1!
#255000
0!
#260000
b110 "
b110 %
1!
#265000
0!
#270000
b111 "
b111 %
1!
#275000
0!
#280000
b1000 "
b1000 %
1!
#285000
0!
#290000
b1001 "
b1001 %
1!
#295000
0!
#300000
b1010 "
b1010 %
1!
#305000
0!
#310000
b1011 "
b1011 %
1!
#315000
0!
#320000
b1100 "
b1100 %
1!
#325000
0!
#330000
b1101 "
b1101 %
1!
#335000
0!
#340000
b1110 "
b1110 %
1!
#345000
0!
#350000
b1111 "
b1111 %
1!
#355000
0!
#360000
b0 "
b0 %
1!
#365000
0!
#370000
b1 "
b1 %
1!
#375000
0!
#380000
b10 "
b10 %
1!
#385000
0!
#390000
b11 "
b11 %
1!
#395000
0!
#400000
b100 "
b100 %
1!
#405000
0!
#410000
b101 "
b101 %
1!
#415000
0!
#420000
b110 "
b110 %
1!
#425000
0!
#430000
b111 "
b111 %
1!
#435000
0!
#440000
b1000 "
b1000 %
1!
#445000
0!
#450000
b1001 "
b1001 %
1!
#455000
0!
#460000
b1010 "
b1010 %
1!
#465000
0!
#470000
b1011 "
b1011 %
1!
#475000
0!
#480000
b1100 "
b1100 %
1!
#485000
0!
#490000
b1101 "
b1101 %
1!
#495000
0!
#500000
b1110 "
b1110 %
1!
#505000
0!
#510000
b1111 "
b1111 %
1!
#515000
0!
#520000
b0 "
b0 %
1!
#525000
0!
#530000
b1 "
b1 %
1!
#535000
0!
#540000
b10 "
b10 %
1!
#540001
1$
b11 #
#545001
0!
#550001
b0 "
b0 %
1!
#555001
0!
#560001
1!
#565001
0!
#570001
1!
#575001
0!
#580001
1!
#585001
0!
#590001
b1111 "
b1111 %
1!
0$
#595001
0!
#600001
b1110 "
b1110 %
1!
#605001
0!
#610001
b1101 "
b1101 %
1!
#615001
0!
#620001
b1100 "
b1100 %
1!
#625001
0!
#630001
b1011 "
b1011 %
1!
#635001
0!
#640001
b1010 "
b1010 %
1!
#645001
0!
#650001
b1001 "
b1001 %
1!
#655001
0!
#660001
b1000 "
b1000 %
1!
#665001
0!
#670001
b111 "
b111 %
1!
#675001
0!
#680001
b110 "
b110 %
1!
#685001
0!
#690001
b101 "
b101 %
1!
#695001
0!
#700001
b100 "
b100 %
1!
#705001
0!
#710001
b11 "
b11 %
1!
#715001
0!
#720001
b10 "
b10 %
1!
#725001
0!
#730001
b1 "
b1 %
1!
#735001
0!
#740001
b0 "
b0 %
1!
#745001
0!
#750001
b1111 "
b1111 %
1!
#755001
0!
#760001
b1110 "
b1110 %
1!
#765001
0!
#770001
b1101 "
b1101 %
1!
#775001
0!
#780001
b1100 "
b1100 %
1!
#785001
0!
#790001
b1011 "
b1011 %
1!
#795001
0!
#800001
b1010 "
b1010 %
1!
#805001
0!
#810001
b1001 "
b1001 %
1!
#815001
0!
#820001
b1000 "
b1000 %
1!
#825001
0!
#830001
b111 "
b111 %
1!
#835001
0!
#840001
b110 "
b110 %
1!
#845001
0!
#850001
b101 "
b101 %
1!
#855001
0!
#860001
b100 "
b100 %
1!
#865001
0!
#870001
b11 "
b11 %
1!
#875001
0!
#880001
b10 "
b10 %
1!
#885001
0!
#890001
b1 "
b1 %
1!
#895001
0!
#900001
b0 "
b0 %
1!
#905001
0!
#910001
b1111 "
b1111 %
1!
#915001
0!
#920001
b1110 "
b1110 %
1!
#925001
0!
#930001
b1101 "
b1101 %
1!
#935001
0!
#940001
b1100 "
b1100 %
1!
#945001
0!
#950001
b1011 "
b1011 %
1!
#955001
0!
#960001
b1010 "
b1010 %
1!
#965001
0!
#970001
b1001 "
b1001 %
1!
#975001
0!
#980001
b1000 "
b1000 %
1!
#985001
0!
#990001
b111 "
b111 %
1!
#995001
0!
#1000001
b110 "
b110 %
1!
#1005001
0!
#1010001
b101 "
b101 %
1!
#1015001
0!
#1020001
b100 "
b100 %
1!
#1025001
0!
#1030001
b11 "
b11 %
1!
#1035001
0!
#1040001
b10 "
b10 %
1!
#1045001
0!
#1050001
b1 "
b1 %
1!
#1055001
0!
#1060001
b0 "
b0 %
1!
#1065001
0!
#1070001
b1111 "
b1111 %
1!
#1075001
0!
#1080001
b1110 "
b1110 %
1!
#1080002
1$
b0 #
#1085002
0!
#1090002
b0 "
b0 %
1!
#1095002
0!
#1100002
1!
#1105002
0!
#1110002
1!
#1115002
0!
#1120002
1!
#1125002
0!
#1130002
b1 "
b1 %
1!
b1 #
0$
#1135002
0!
#1140002
b10 "
b10 %
1!
#1145002
0!
#1150002
b11 "
b11 %
1!
#1155002
0!
#1160002
b100 "
b100 %
1!
#1165002
0!
#1170002
b101 "
b101 %
1!
#1175002
0!
#1180002
b110 "
b110 %
1!
#1185002
0!
#1190002
b111 "
b111 %
1!
#1195002
0!
#1200002
b1000 "
b1000 %
1!
#1205002
0!
#1210002
b1001 "
b1001 %
1!
#1215002
0!
#1220002
b1010 "
b1010 %
1!
#1225002
0!
#1230002
b1011 "
b1011 %
1!
#1235002
0!
#1240002
b1100 "
b1100 %
1!
#1245002
0!
#1250002
b1101 "
b1101 %
1!
#1255002
0!
#1260002
b1110 "
b1110 %
1!
#1265002
0!
#1270002
b1111 "
b1111 %
1!
#1275002
0!
#1280002
b11 #
b0 "
b0 %
1!
#1285002
0!
#1290002
b1111 "
b1111 %
1!
#1295002
0!
#1300002
b1110 "
b1110 %
1!
#1305002
0!
#1310002
b1101 "
b1101 %
1!
#1315002
0!
#1320002
b1100 "
b1100 %
1!
#1325002
0!
#1330002
b1011 "
b1011 %
1!
#1335002
0!
#1340002
b1010 "
b1010 %
1!
#1345002
0!
#1350002
b1001 "
b1001 %
1!
#1355002
0!
#1360002
b1000 "
b1000 %
1!
#1365002
0!
#1370002
b111 "
b111 %
1!
#1375002
0!
#1380002
b110 "
b110 %
1!
#1385002
0!
#1390002
b101 "
b101 %
1!
#1395002
0!
#1400002
b100 "
b100 %
1!
#1405002
0!
#1410002
b11 "
b11 %
1!
#1415002
0!
#1420002
b10 "
b10 %
1!
#1425002
0!
#1430002
b1 "
b1 %
1!
#1435002
0!
#1440002
b0 #
b0 "
b0 %
1!
#1445002
0!
#1450002
b1 #
1!
#1455002
0!
#1460002
b1 "
b1 %
1!
#1465002
0!
#1470002
b10 "
b10 %
1!
#1475002
0!
#1480002
b11 "
b11 %
1!
#1485002
0!
#1490002
b100 "
b100 %
1!
#1495002
0!
#1500002
b101 "
b101 %
1!
#1505002
0!
#1510002
b110 "
b110 %
1!
#1515002
0!
#1520002
b111 "
b111 %
1!
#1525002
0!
#1530002
b1000 "
b1000 %
1!
#1535002
0!
#1540002
b1001 "
b1001 %
1!
#1545002
0!
#1550002
b1010 "
b1010 %
1!
#1555002
0!
#1560002
b1011 "
b1011 %
1!
#1565002
0!
#1570002
b1100 "
b1100 %
1!
#1575002
0!
#1580002
b1101 "
b1101 %
1!
#1585002
0!
#1590002
b1110 "
b1110 %
1!
#1595002
0!
#1600002
b11 #
b1111 "
b1111 %
1!
#1605002
0!
#1610002
b1110 "
b1110 %
1!
#1615002
0!
#1620002
b1101 "
b1101 %
1!
